{"created": 1762713755.8865616, "duration": 0.5676455497741699, "exitcode": 0, "root": "C:\\Users\\mocha\\Documents\\Assignments\\COMPSCI520\\COMPSCI520-Exercise-2", "environment": {}, "summary": {"passed": 5, "total": 5, "collected": 5}, "collectors": [{"nodeid": "", "outcome": "passed", "result": [{"nodeid": "scripts/cot_results_llama_3", "type": "Dir"}]}, {"nodeid": "scripts/cot_results_llama_3/cot_results_llama_3", "outcome": "passed", "result": []}, {"nodeid": "scripts/cot_results_llama_3/tests/test_below_zero_0.py", "outcome": "passed", "result": [{"nodeid": "scripts/cot_results_llama_3/tests/test_below_zero_0.py::test_below_zero_0", "type": "Function", "lineno": 4}]}, {"nodeid": "scripts/cot_results_llama_3/tests/test_below_zero_1.py", "outcome": "passed", "result": [{"nodeid": "scripts/cot_results_llama_3/tests/test_below_zero_1.py::test_below_zero_1", "type": "Function", "lineno": 4}]}, {"nodeid": "scripts/cot_results_llama_3/tests/test_below_zero_2.py", "outcome": "passed", "result": [{"nodeid": "scripts/cot_results_llama_3/tests/test_below_zero_2.py::test_below_zero_2", "type": "Function", "lineno": 4}]}, {"nodeid": "scripts/cot_results_llama_3/tests/test_below_zero_3.py", "outcome": "passed", "result": [{"nodeid": "scripts/cot_results_llama_3/tests/test_below_zero_3.py::test_below_zero_3", "type": "Function", "lineno": 4}]}, {"nodeid": "scripts/cot_results_llama_3/tests/test_below_zero_4.py", "outcome": "passed", "result": [{"nodeid": "scripts/cot_results_llama_3/tests/test_below_zero_4.py::test_below_zero_4", "type": "Function", "lineno": 4}]}, {"nodeid": "scripts/cot_results_llama_3/tests/test_cot_results_llama_3.py", "outcome": "passed", "result": []}, {"nodeid": "scripts/cot_results_llama_3/tests", "outcome": "passed", "result": [{"nodeid": "scripts/cot_results_llama_3/tests/test_below_zero_0.py", "type": "Module"}, {"nodeid": "scripts/cot_results_llama_3/tests/test_below_zero_1.py", "type": "Module"}, {"nodeid": "scripts/cot_results_llama_3/tests/test_below_zero_2.py", "type": "Module"}, {"nodeid": "scripts/cot_results_llama_3/tests/test_below_zero_3.py", "type": "Module"}, {"nodeid": "scripts/cot_results_llama_3/tests/test_below_zero_4.py", "type": "Module"}, {"nodeid": "scripts/cot_results_llama_3/tests/test_cot_results_llama_3.py", "type": "Module"}]}, {"nodeid": "scripts/cot_results_llama_3", "outcome": "passed", "result": [{"nodeid": "scripts/cot_results_llama_3/cot_results_llama_3", "type": "Package"}, {"nodeid": "scripts/cot_results_llama_3/tests", "type": "Package"}]}], "tests": [{"nodeid": "scripts/cot_results_llama_3/tests/test_below_zero_0.py::test_below_zero_0", "lineno": 4, "outcome": "passed", "keywords": ["test_below_zero_0", "test_below_zero_0.py", "tests", "cot_results_llama_3", "scripts", "COMPSCI520-Exercise-2", ""], "setup": {"duration": 0.0012332999613136053, "outcome": "passed"}, "metadata": {"test_accuracy": 0.299003322255825, "name": "test_below_zero_0"}, "call": {"duration": 0.009378100046887994, "outcome": "passed"}, "teardown": {"duration": 0.000408999971114099, "outcome": "passed"}}, {"nodeid": "scripts/cot_results_llama_3/tests/test_below_zero_1.py::test_below_zero_1", "lineno": 4, "outcome": "passed", "keywords": ["test_below_zero_1", "test_below_zero_1.py", "tests", "cot_results_llama_3", "scripts", "COMPSCI520-Exercise-2", ""], "setup": {"duration": 0.0007811000104993582, "outcome": "passed"}, "metadata": {"test_accuracy": 0.5348837209243091, "name": "test_below_zero_1"}, "call": {"duration": 0.006995100062340498, "outcome": "passed"}, "teardown": {"duration": 0.0009374000364914536, "outcome": "passed"}}, {"nodeid": "scripts/cot_results_llama_3/tests/test_below_zero_2.py::test_below_zero_2", "lineno": 4, "outcome": "passed", "keywords": ["test_below_zero_2", "test_below_zero_2.py", "tests", "cot_results_llama_3", "scripts", "COMPSCI520-Exercise-2", ""], "setup": {"duration": 0.0005239000311121345, "outcome": "passed"}, "metadata": {"test_accuracy": 0.7021040974451594, "name": "test_below_zero_2"}, "call": {"duration": 0.00675630010664463, "outcome": "passed"}, "teardown": {"duration": 0.0005462999688461423, "outcome": "passed"}}, {"nodeid": "scripts/cot_results_llama_3/tests/test_below_zero_3.py::test_below_zero_3", "lineno": 4, "outcome": "passed", "keywords": ["test_below_zero_3", "test_below_zero_3.py", "tests", "cot_results_llama_3", "scripts", "COMPSCI520-Exercise-2", ""], "setup": {"duration": 0.00040479993913322687, "outcome": "passed"}, "metadata": {"test_accuracy": 0.9999999999889257, "name": "test_below_zero_3"}, "call": {"duration": 0.004396500065922737, "outcome": "passed"}, "teardown": {"duration": 0.00042150006629526615, "outcome": "passed"}}, {"nodeid": "scripts/cot_results_llama_3/tests/test_below_zero_4.py::test_below_zero_4", "lineno": 4, "outcome": "passed", "keywords": ["test_below_zero_4", "test_below_zero_4.py", "tests", "cot_results_llama_3", "scripts", "COMPSCI520-Exercise-2", ""], "setup": {"duration": 0.0005582000594586134, "outcome": "passed"}, "metadata": {"test_accuracy": 0.7054263565813352, "name": "test_below_zero_4"}, "call": {"duration": 0.0035670000361278653, "outcome": "passed"}, "teardown": {"duration": 0.0007835999131202698, "outcome": "passed"}}]}